perte/__init__.py
perte/angular_losses.py
perte/focal_losses.py
perte/ldam_loss.py
perte/poly_loss.py
perte/recall_loss.py
perte/triplet_losses.py
perte-0.1.3.dist-info/LICENSE.txt
perte-0.1.3.dist-info/METADATA
perte-0.1.3.dist-info/WHEEL
perte-0.1.3.dist-info/top_level.txt
perte-0.1.3.dist-info/RECORD
