Metadata-Version: 2.1
Name: perte
Version: 0.1.3
Summary: A fast way to use the diverse loss functions in deep learning
Home-page: https://github.com/taindp98/perte
Download-URL: https://github.com/taindp98/perte/archive/refs/tags/v.0.1.2.tar.gz
Author: Rémi NGUYEN
Author-email: taindp98@gmail.com
License: MIT
Keywords: loss-function,discrimination
Classifier: Development Status :: 3 - Alpha
Classifier: Intended Audience :: Developers
Classifier: Topic :: Software Development :: Build Tools
Classifier: License :: OSI Approved :: MIT License
Classifier: Programming Language :: Python :: 3
Classifier: Programming Language :: Python :: 3.4
Classifier: Programming Language :: Python :: 3.5
Classifier: Programming Language :: Python :: 3.6
Classifier: Programming Language :: Python :: 3.7
Classifier: Programming Language :: Python :: 3.8
Classifier: Programming Language :: Python :: 3.9
License-File: LICENSE.txt
Requires-Dist: pip
Requires-Dist: packaging
Requires-Dist: torch
Requires-Dist: numpy
